hippunfold/__init__.py
hippunfold/download_models.py
hippunfold/run.py
hippunfold/config/nnunet_model_urls.yml
hippunfold/config/snakebids.yml
hippunfold/resources/Training_Instructions.md
hippunfold/resources/desc-flipLR_type-itk_xfm.txt
hippunfold/resources/desc-subfields_dseg.tsv
hippunfold/resources/dseg.tsv
hippunfold/resources/example_sbatch.sh
hippunfold/resources/fineTune_UNet.sh
hippunfold/resources/write_config_NiftyNet.py
hippunfold/resources/CITI168/CoronalOblique_rigid.txt
hippunfold/resources/CITI168/Mask_300umCoronalOblique_hemi-L.nii.gz
hippunfold/resources/CITI168/Mask_300umCoronalOblique_hemi-R.nii.gz
hippunfold/resources/CITI168/T1w_300umCoronalOblique_hemi-L.nii.gz
hippunfold/resources/CITI168/T1w_300umCoronalOblique_hemi-R.nii.gz
hippunfold/resources/CITI168/T1w_head_700um.nii.gz
hippunfold/resources/CITI168/T2w_300umCoronalOblique_hemi-L.nii.gz
hippunfold/resources/CITI168/T2w_300umCoronalOblique_hemi-R.nii.gz
hippunfold/resources/bigbrain/BigBrain_ManualSubfields.png
hippunfold/resources/bigbrain/BigBrain_ManualSubfieldsUnfolded.mat
hippunfold/resources/bigbrain/BigBrain_ManualSubfieldsUnfolded_254x126.border
hippunfold/resources/bigbrain/BigBrain_ManualSubfieldsUnfolded_254x126.label.gii
hippunfold/resources/bigbrain/BigBrain_ManualSubfieldsUnfolded_254x126.shape.gii
hippunfold/resources/bigbrain/sub-bigbrain_hemi-L_subfields.border
hippunfold/resources/bigbrain/sub-bigbrain_hemi-L_subfields.label.gii
hippunfold/resources/bigbrain/sub-bigbrain_hemi-R_subfields.border
hippunfold/resources/bigbrain/sub-bigbrain_hemi-R_subfields.label.gii
hippunfold/resources/bigbrain/sub-bigbrain_labellist.txt
hippunfold/resources/tpl-upenn/.gitignore
hippunfold/resources/tpl-upenn/Snakefile
hippunfold/resources/tpl-upenn/dag.pdf
hippunfold/resources/tpl-upenn/tpl-upenn_desc-hipptissue_dseg.nii.gz
hippunfold/resources/tpl-upenn/tpl-upenn_dir-AP_coords.nii.gz
hippunfold/resources/tpl-upenn/tpl-upenn_dir-IO_coords.nii.gz
hippunfold-0.5.11.dist-info/METADATA
hippunfold-0.5.11.dist-info/WHEEL
hippunfold-0.5.11.dist-info/entry_points.txt
hippunfold-0.5.11.dist-info/top_level.txt
hippunfold-0.5.11.dist-info/RECORD
