Metadata-Version: 2.1
Name: hippunfold
Version: 0.5.11
Summary: Snakemake BIDS app for hippocampal unfolding & subfield segmentation
Home-page: https://github.com/khanlab/hippunfold
Author: Jordan DeKraker & Ali Khan
Author-email: ali.khan@uwo.ca
License: UNKNOWN
Platform: UNKNOWN
Classifier: Programming Language :: Python :: 3
Classifier: License :: OSI Approved :: MIT License
Classifier: Operating System :: OS Independent
Requires-Python: >=3.7
Requires-Dist: snakebids (>=0.3.10)
Requires-Dist: snakemake (>=6.5.2)
Requires-Dist: nnunet-inference-on-cpu-and-gpu (==1.6.6)
Requires-Dist: numpy (>=1.20.2)
Requires-Dist: astropy
Requires-Dist: appdirs
Requires-Dist: pandas
Requires-Dist: nibabel
Requires-Dist: scipy
Requires-Dist: nilearn
Requires-Dist: seaborn
Requires-Dist: jinja2
Requires-Dist: pygraphviz
Requires-Dist: pygments
Requires-Dist: scikit-fmm
